emzed_spyder/__init__.py
emzed_spyder/patch_all.py
emzed_spyder/patch_config.py
emzed_spyder/patch_gui.py
emzed_spyder/patch_remote_kernel_startup.py
emzed_spyder/remote_interpreter_startup.py
emzed_spyder/start.py
emzed_spyder/utils.py
emzed_spyder/assets/emzed_icon.png
emzed_spyder/assets/splash.png
emzed_spyder/assets/splash.svg
emzed_spyder/emzed3_examples/README.txt
emzed_spyder/emzed_package_template/cookiecutter.json
emzed_spyder/emzed_package_template/{{cookiecutter.directory_name}}/LICENSE.txt
emzed_spyder/emzed_package_template/{{cookiecutter.directory_name}}/MANIFEST.in
emzed_spyder/emzed_package_template/{{cookiecutter.directory_name}}/requirements_dev.txt
emzed_spyder/emzed_package_template/{{cookiecutter.directory_name}}/setup.pytemplate
emzed_spyder/emzed_package_template/{{cookiecutter.directory_name}}/tox.ini
emzed_spyder/emzed_package_template/{{cookiecutter.directory_name}}/src/emzed_ext_{{cookiecutter.pkg_name}}/__init__.pytemplate
emzed_spyder/emzed_package_template/{{cookiecutter.directory_name}}/src/emzed_ext_{{cookiecutter.pkg_name}}/example_module.pytemplate
emzed_spyder/emzed_package_template/{{cookiecutter.directory_name}}/src/emzed_ext_{{cookiecutter.pkg_name}}/data/readme.txt
emzed_spyder/emzed_package_template/{{cookiecutter.directory_name}}/tests/test_{{cookiecutter.pkg_name}}.pytemplate
emzed_spyder/emzed_spyder_kernels/emzed_spyder_kernels.py
emzed_spyder/emzed_spyder_kernels/setup.py
emzed_spyder-3.0.0a18.dist-info/METADATA
emzed_spyder-3.0.0a18.dist-info/WHEEL
emzed_spyder-3.0.0a18.dist-info/entry_points.txt
emzed_spyder-3.0.0a18.dist-info/top_level.txt
emzed_spyder-3.0.0a18.dist-info/RECORD
