Metadata-Version: 2.2
Name: emzed-spyder
Version: 3.0.0a18
Summary: emzed IDE, see also https://emzed.ethz.ch
Home-page: https://emzed.ethz.ch
Author: Uwe Schmitt
Author-email: uwe.schmitt@id.ethz.ch
License: MIT
Requires-Dist: alabaster==0.7.13
Requires-Dist: astroid==2.15.6
Requires-Dist: asttokens==2.2.1
Requires-Dist: atomicwrites==1.4.1
Requires-Dist: attrs==23.1.0
Requires-Dist: babel==2.12.1
Requires-Dist: backcall==0.2.0
Requires-Dist: bcrypt==4.0.1
Requires-Dist: binaryornot==0.4.4
Requires-Dist: black==23.7.0
Requires-Dist: bleach==6.0.0
Requires-Dist: certifi==2023.5.7
Requires-Dist: cffi>=1.17
Requires-Dist: chardet==3.0.4
Requires-Dist: charset-normalizer==3.2.0
Requires-Dist: click==8.1.4
Requires-Dist: cloudpickle==2.2.1
Requires-Dist: comm==0.1.3
Requires-Dist: cookiecutter==2.2.3
Requires-Dist: cryptography==41.0.2
Requires-Dist: debugpy==1.6.7
Requires-Dist: decorator==5.1.1
Requires-Dist: defusedxml==0.7.1
Requires-Dist: diff-match-patch==20230430
Requires-Dist: dill==0.3.6
Requires-Dist: docstring-to-markdown==0.12
Requires-Dist: executing==1.2.0
Requires-Dist: fastjsonschema==2.17.1
Requires-Dist: flake8==6.0.0
Requires-Dist: idna==3.4
Requires-Dist: imagesize==1.4.1
Requires-Dist: importlib-metadata==6.8.0
Requires-Dist: inflection==0.5.1
Requires-Dist: intervaltree==3.1.0
Requires-Dist: ipykernel==6.24.0
Requires-Dist: ipython==8.14.0
Requires-Dist: ipython-genutils==0.2.0
Requires-Dist: isort==5.12.0
Requires-Dist: jedi==0.18.2
Requires-Dist: jinja2==3.1.2
Requires-Dist: jsonschema==4.18.2
Requires-Dist: jsonschema-specifications==2023.6.1
Requires-Dist: jupyter-client==8.3.0
Requires-Dist: jupyter-core==5.3.1
Requires-Dist: jupyterlab-pygments==0.2.2
Requires-Dist: keyring==24.2.0
Requires-Dist: lazy-object-proxy==1.9.0
Requires-Dist: markupsafe==2.1.3
Requires-Dist: matplotlib-inline==0.1.6
Requires-Dist: mccabe==0.7.0
Requires-Dist: mistune==3.0.1
Requires-Dist: more-itertools==9.1.0
Requires-Dist: mypy-extensions==1.0.0
Requires-Dist: nbclient==0.8.0
Requires-Dist: nbconvert==7.6.0
Requires-Dist: nbformat==5.9.1
Requires-Dist: nest-asyncio==1.5.6
Requires-Dist: numpy
Requires-Dist: rtree>=0.9.7
Requires-Dist: packaging==23.1
Requires-Dist: pandas
Requires-Dist: pandocfilters==1.5.0
Requires-Dist: parso==0.8.3
Requires-Dist: pathspec==0.11.1
Requires-Dist: pexpect==4.8.0
Requires-Dist: pickleshare==0.7.5
Requires-Dist: platformdirs
Requires-Dist: pluggy
Requires-Dist: prompt-toolkit==3.0.39
Requires-Dist: psutil==5.9.5
Requires-Dist: ptyprocess==0.7.0
Requires-Dist: pure-eval==0.2.2
Requires-Dist: pycodestyle==2.10.0
Requires-Dist: pycparser==2.21
Requires-Dist: pydocstyle==6.3.0
Requires-Dist: pyflakes==3.0.1
Requires-Dist: pygments==2.15.1
Requires-Dist: pylint==2.17.4
Requires-Dist: pylint-venv==3.0.2
Requires-Dist: pyls-spyder==0.4.0
Requires-Dist: pyqt5
Requires-Dist: pyqt5-qt5
Requires-Dist: pyqt5-sip==12.13.0
Requires-Dist: pyqtwebengine
Requires-Dist: python-dateutil==2.8.2
Requires-Dist: python-jsonrpc-server==0.4.0
Requires-Dist: python-lsp-black==1.3.0
Requires-Dist: python-lsp-jsonrpc==1.0.0
Requires-Dist: python-lsp-server[all]==1.7.4
Requires-Dist: python-slugify==8.0.1
Requires-Dist: pytoolconfig[global]==1.2.5
Requires-Dist: pytz==2023.3
Requires-Dist: pyyaml>=6.0.2
Requires-Dist: pyzmq>=26
Requires-Dist: qdarkstyle==3.1
Requires-Dist: qstylizer==0.2.2
Requires-Dist: qtawesome==1.2.3
Requires-Dist: qtconsole==5.4.3
Requires-Dist: qtpy==2.3.1
Requires-Dist: referencing==0.29.1
Requires-Dist: requests==2.31.0
Requires-Dist: rope==1.9.0
Requires-Dist: setproctitle==1.3.2
Requires-Dist: six==1.16.0
Requires-Dist: snowballstemmer==2.2.0
Requires-Dist: sortedcontainers==2.4.0
Requires-Dist: soupsieve==2.4.1
Requires-Dist: sphinx
Requires-Dist: spyder==5.4.3
Requires-Dist: spyder-kernels==2.4.4
Requires-Dist: stack-data==0.6.2
Requires-Dist: text-unidecode==1.3
Requires-Dist: textdistance==4.5.0
Requires-Dist: three-merge==0.1.1
Requires-Dist: tinycss2==1.2.1
Requires-Dist: tomli==2.0.1
Requires-Dist: tomlkit==0.11.8
Requires-Dist: tornado==6.3.2
Requires-Dist: traitlets==5.9.0
Requires-Dist: typing-extensions==4.7.1
Requires-Dist: tzdata==2023.3
Requires-Dist: ujson==5.8.0
Requires-Dist: urllib3==2.0.3
Requires-Dist: watchdog>=6
Requires-Dist: wcwidth==0.2.6
Requires-Dist: webencodings==0.5.1
Requires-Dist: whatthepatch==1.0.5
Requires-Dist: wrapt==1.15.0
Requires-Dist: wurlitzer==3.0.3
Requires-Dist: yapf==0.40.1
Requires-Dist: zipp==3.16.1
Dynamic: author
Dynamic: author-email
Dynamic: description
Dynamic: home-page
Dynamic: license
Dynamic: requires-dist
Dynamic: summary
